packet_helper/__init__.py
scapy_helper/__init__.py
scapy_helper/chexdump.py
scapy_helper/compare.py
scapy_helper/hexdump.py
scapy_helper/main.py
scapy_helper/helpers/__init__.py
scapy_helper/helpers/depracated.py
scapy_helper/helpers/ip.py
scapy_helper/helpers/mac.py
scapy_helper/helpers/to_dict.py
scapy_helper/helpers/to_list.py
scapy_helper/helpers/utils.py
scapy_helper/test_case_extensions/__init__.py
scapy_helper/test_case_extensions/packet_assert.py
scapy_helper/test_case_extensions/pytest_assert.py
scapy_helper/utils/__init__.py
scapy_helper/utils/hhstrip.py
scapy_helper/utils/hstrip.py
scapy_helper-0.14.8.dist-info/LICENSE
scapy_helper-0.14.8.dist-info/METADATA
scapy_helper-0.14.8.dist-info/WHEEL
scapy_helper-0.14.8.dist-info/entry_points.txt
scapy_helper-0.14.8.dist-info/top_level.txt
scapy_helper-0.14.8.dist-info/RECORD
